evoml/__init__.py
evoml/evoml.py
evoml/datasets/__init__.py
evoml/datasets/_base.py
evoml/framework/__init__.py
evoml/framework/constant.py
evoml/framework/classification/__init__.py
evoml/framework/classification/_base.py
evoml/framework/evocc/__init__.py
evoml/framework/evocc/_evocc.py
evoml/framework/evocc/constant.py
evoml/framework/evocc/classification/__init__.py
evoml/framework/evocc/classification/_base.py
evoml/framework/evocc/metrics/__init__.py
evoml/framework/evocc/metrics/_base.py
evoml/framework/evocc/utils/__init__.py
evoml/framework/evocc/utils/_base.py
evoml/framework/evocluster/__init__.py
evoml/framework/evocluster/_cluster_detection.py
evoml/framework/evocluster/_evocluster.py
evoml/framework/evocluster/_measures.py
evoml/framework/evocluster/_objectives.py
evoml/framework/evocluster/_plot_boxplot.py
evoml/framework/evocluster/_plot_convergence.py
evoml/framework/evocluster/_solution.py
evoml/framework/evocluster/optimizers/CBAT.py
evoml/framework/evocluster/optimizers/CCS.py
evoml/framework/evocluster/optimizers/CFFA.py
evoml/framework/evocluster/optimizers/CGA.py
evoml/framework/evocluster/optimizers/CGWO.py
evoml/framework/evocluster/optimizers/CMFO.py
evoml/framework/evocluster/optimizers/CMVO.py
evoml/framework/evocluster/optimizers/CPSO.py
evoml/framework/evocluster/optimizers/CSSA.py
evoml/framework/evocluster/optimizers/CWOA.py
evoml/framework/evocluster/optimizers/__init__.py
evoml/framework/evonn/__init__.py
evoml/framework/metrics/__init__.py
evoml/framework/metrics/_base.py
evoml/framework/utils/__init__.py
evoml/framework/utils/_base.py
evoml/utils/__init__.py
evoml/utils/_base.py
evoml-0.1.0.dist-info/AUTHORS.rst
evoml-0.1.0.dist-info/LICENSE
evoml-0.1.0.dist-info/METADATA
evoml-0.1.0.dist-info/WHEEL
evoml-0.1.0.dist-info/top_level.txt
evoml-0.1.0.dist-info/RECORD
