Metadata-Version: 2.1
Name: evoml
Version: 0.1.0
Summary: EvoML Framework
Home-page: https://github.com/housecricket/evoml
Author: Dang Trung Anh
Author-email: dangtrunganh@gmail.com
License: MIT license
Keywords: evoml
Classifier: Development Status :: 2 - Pre-Alpha
Classifier: Intended Audience :: Developers
Classifier: License :: OSI Approved :: MIT License
Classifier: Natural Language :: English
Classifier: Programming Language :: Python :: 3
Classifier: Programming Language :: Python :: 3.6
Classifier: Programming Language :: Python :: 3.7
Classifier: Programming Language :: Python :: 3.8
Requires-Python: >=3.6
License-File: LICENSE
License-File: AUTHORS.rst
Requires-Dist: sklearn
Requires-Dist: numpy
Requires-Dist: scipy
Requires-Dist: matplotlib
Requires-Dist: pandas
Requires-Dist: imblearn
